{
  "reviews": [{
    "reviewer": {
      "displayName": "Hussam Aldeen MAHMOUD"
    },
    "starRating": "FIVE",
    "comment": "ุตุงููู ุฑุงุฆุน ู ุชุนุงูู ุฑุงุฆุน ูู ุงูููุธููู\n\n(Translated by Google)\nGreat salon and great service from the staff",
    "createTime": "2025-09-05T04:31:26.713103Z",
    "updateTime": "2025-09-05T04:32:02.364629Z",
    "reviewReply": {
      "comment": "ูุณุนุฏูุง ุฌุฏูุง ุฑุฃูู ูุง ุญุณุงู ๐น\nุณุนูุฏูู ุฅูู ูููุช ุนูุฏูุง ุงูุฎุฏูุฉ ูุงูุฃุฌูุงุก ุงููู ุชููู ููู ๐\nุชุนูููุงุชู ุชุนุทููุง ุฏุงูุน ุฃูุจุฑ ูุณุชูุฑ ุนูู ููุณ ุงููุณุชูู ููุทูุฑ ุฃูุซุฑ ๐โจ\nููุฑุชูุง ููุชููู ูุดููู ุฏูููุง.",
      "updateTime": "2025-09-07T22:29:19.037841Z"
    },
    "name": "accounts/101966824514574841442/locations/17375006377495534857/reviews/Ci9DQUlRQUNvZENodHljRjlvT2tJNFdWUXpZbXA1Y0ZOdlIya3ljR1ZSV1RaaWRXYxAB"
  }, {
    "reviewer": {
      "displayName": "Turki alharthi"
    },
    "starRating": "FIVE",
    "createTime": "2025-09-03T19:08:41.589323Z",
    "updateTime": "2025-09-03T19:08:41.589323Z",
    "reviewReply": {
      "comment": "๐ฅฐ๐บ",
      "updateTime": "2025-09-07T22:29:28.804293Z"
    },
    "name": "accounts/101966824514574841442/locations/17375006377495534857/reviews/Ci9DQUlRQUNvZENodHljRjlvT2xOUVYyMWZNa281YkROcVNtMW5VWGREZEhGa2JrRRAB"
  }, {
    "reviewer": {
      "displayName": "ุนุจุฏุงููู ุงููุงููู"
    },
    "starRating": "FIVE",
    "comment": "ูุงูุช ุชุฌุฑุจุฉ ุฑุงุฆุนุฉ ุดูุฑุง โค๏ธโค๏ธ\n\n(Translated by Google)\nIt was a great experience, thank you โค๏ธโค๏ธ",
    "createTime": "2025-09-01T21:24:09.405470Z",
    "updateTime": "2025-09-01T21:24:09.405470Z",
    "reviewReply": {
      "comment": "ุดูุฑูุง ูู ูุง ุนุจุฏุงููู ๐น\nุณุนูุฏูู ุฅููุง ูุงูุช ุชุฌุฑุจุฉ ุฑุงุฆุนุฉ ููุฑุญุจ ููู ุฏุงุฆููุง ๐โจ",
      "updateTime": "2025-09-07T22:30:39.014376Z"
    },
    "name": "accounts/101966824514574841442/locations/17375006377495534857/reviews/Ci9DQUlRQUNvZENodHljRjlvT25wdFUyTk1UV2RhV2tsemFWUldjR1ozV1hjM1NtYxAB"
  }, {
    "reviewer": {
      "displayName": "K_RiftX"
    },
    "starRating": "FIVE",
    "comment": "ูุญู ุฃูู ููุญูุงูุฉ ูุชููุฒ ุจุงููุธุงูุฉ ูุงูุงุญุชุฑุงููุฉ ุงูุนุงููุฉ. ุงูุญูุงู ุฎุงูุฏ ูุงู ูุจุฏุนูุง ูู ุนูููุ ุงูุชู ุจุฃุฏู ุงูุชูุงุตูู ููุฏู ุฎุฏูุฉ ุฑุงููุฉ ุชุณุชุญู ุงูุฅุดุงุฏุฉ. ุงูุฃุณุนุงุฑ ููุงุณุจุฉุ ูุงูููุงู ูุฑูุญ ููุฑุชุจ. ุชุฌุฑุจุฉ ููุชุงุฒุฉ ูุฃูุตุญ ุจุฒูุงุฑุชู ูุจุฎุงุตุฉ ุนูุฏ ุงูุญูุงู ุฎุงูุฏ.\n\n(Translated by Google)\nAkka Barber Shop is characterized by cleanliness and high professionalism. Barber Khaled was creative in his work, paying attention to the smallest details, and providing high-quality service that deserves praise. The prices are reasonable, and the place is comfortable and tidy. It was an excellent experience, and I highly recommend visiting it, especially with barber Khaled.",
    "createTime": "2025-08-29T19:09:08.404424Z",
    "updateTime": "2025-08-29T19:09:08.404424Z",
    "reviewReply": {
      "comment": "ุดูุฑูุง ูุง ุฎุงูุฏ ุนูู ุฑุฃูู ุงูุฑุงุฆุน ูุชูุงุตููู ุงูุฌูููุฉ ๐น\nุณุนูุฏูู ุฅูู ูููุช ุนูุฏูุง ุงููุธุงูุฉ ูุงูุงุญุชุฑุงููุฉ ุงููู ุชุจุญุซ ุนููุงุ ููุฐุง ุจุงูุถุจุท ูุฏููุง ๐\nุงูุฃุฌูุงุก ุงููุฑูุญุฉ ูุงูุฎุฏูุฉ ุงูุฑุงููุฉ ุฃุณุงุณ ูุญุฑุต ุนููู ูู ูู ุฒูุงุฑุฉ ๐โจ\nููุฑุชูุง ููุดููู ุฏูููุง ุนูู ุฃุญุณู ุญุงู.",
      "updateTime": "2025-09-07T22:31:11.981906Z"
    },
    "name": "accounts/101966824514574841442/locations/17375006377495534857/reviews/Ci9DQUlRQUNvZENodHljRjlvT2pOV2VFZENUeTFQTm1NeE1qSk9USFJpWlZSbFdrRRAB"
  }, {
    "reviewer": {
      "displayName": "ูุญูุฏ ุงูุฏูุณุฑู"
    },
    "starRating": "TWO",
    "comment": "ูุนููู\n\n(Translated by Google)\nreasonable",
    "createTime": "2025-08-28T21:35:50.743088Z",
    "updateTime": "2025-08-28T21:35:50.743088Z",
    "reviewReply": {
      "comment": "ุฃููุงู ูุญูุฏ ๐ ูุดูุฑู ุนูู ุฒูุงุฑุชู ููุดุงุฑูุชู ุฑุฃูู ๐\nูุงุถุญ ุฅู ุงูุชุฌุฑุจุฉ ูุง ูุงูุช ุนูุฏ ูุณุชูู ุชููุนุงุชูุ ููุฐุง ุดูุก ูุง ูุฑุถุงู ุฃุจุฏูุง.\nููููุง ูุนุฑู ุฃูุซุฑ ุนู ููุงุญุธุชู ุนุดุงู ูุฑุงุฌุน ุงูููุถูุน ููุทูุฑ ุฎุฏูุชูุง ุจุงูุดูู ุงููู ูููู ููู.\nุชูุงุตูู ูุนูุง ูุณุงุนุฏูุง ูุตูุญ ุฃู ูุตูุฑ ููุถูู ุฅู ุชุฌุฑุจุชู ุงูุฌุงูุฉ ุชููู ุฃูุถู ุจูุซูุฑ ๐โจ",
      "updateTime": "2025-09-07T22:32:07.832053Z"
    },
    "name": "accounts/101966824514574841442/locations/17375006377495534857/reviews/Ci9DQUlRQUNvZENodHljRjlvT2tVM1ltSlFTVGwyZWtWQ1kzVkxVRTA0U1ZOcWRVRRAB"
  }, {
    "reviewer": {
      "displayName": "โซุนุจุฏุงูุฑุญูู ุงูุฑููู (โชD7OOMโฌโ)โฌโ"
    },
    "starRating": "FIVE",
    "comment": "ุญูุงู ูุชููุฒ ุฌูุณูู ูุจูุงููู\nูููุณ ุงูู ูู ุงูููุทูู ุญูุงู ุงุญุชุฑุงูู\n\n(Translated by Google)\nA distinguished Lebanese barber. It\u0027s good that there is a professional barber in the area.",
    "createTime": "2025-08-28T07:42:43.325543Z",
    "updateTime": "2025-08-28T07:42:43.325543Z",
    "reviewReply": {
      "comment": "ุดูุฑูุง ูุง ุนุจุฏุงูุฑุญูู ุนูู ูููุงุชู ุงูุทูุจุฉ ๐น\nุณุนูุฏูู ุฅูู ูุฌุฏุช ุนูุฏูุง ุงูุงุญุชุฑุงููุฉ ุงููู ุชุฏูุฑ ุนูููุง ๐\nูุฌูุฏู ูุดุฑููุง ูุฏุงุฆููุง ูุญุฑุต ูุฎูู ุชุฌุฑุจุชู ูููุฒุฉ ๐โจ",
      "updateTime": "2025-09-07T22:32:31.619270Z"
    },
    "name": "accounts/101966824514574841442/locations/17375006377495534857/reviews/Ci9DQUlRQUNvZENodHljRjlvT21sdlYyTmZTR2xqVnpFelVrMWlkbXRLUTNscGIwRRAB"
  }, {
    "reviewer": {
      "displayName": "ููุฏูุญ ุงูุญุงุฑุซู"
    },
    "starRating": "FIVE",
    "comment": "ูุญู ููุฉ ูู ุงููุธุงูุฉ 10/10\nููุธููู ููุฉ ูู ุงูุงุญุชุฑุงููุฉ ูุฎุตูุตุงู (ุนุจุฏุงูุจุงุณุท โ)\nุดูุฑุงู ููู โฅ๏ธ\n\n(Translated by Google)\nExtremely clean place 10/10\nExtremely professional staff, especially (Abdul Basit โ)\nThank you โฅ๏ธ",
    "createTime": "2025-08-26T15:17:08.102650Z",
    "updateTime": "2025-08-26T15:17:08.102650Z",
    "reviewReply": {
      "comment": "ุงููู ูุณุนุฏู ูุง ููุฏูุญ ๐น\nุณุนูุฏูู ุฅู ุงููุธุงูุฉ ูุงูุงุญุชุฑุงููุฉ ูุงูุช ุจูุณุชูู ุฑุถุงู ๐\nุชุดุฌูุนู ูุนุทููุง ุฏุงูุน ููุงุตู ุจููุณ ุงูููุฉ ููุทูุฑ ุฃูุซุฑ ๐โจ\nููุฑุชูุง ููุดููู ุฏุงูููุง ุนูู ุฎูุฑ.",
      "updateTime": "2025-09-07T22:33:31.860739Z"
    },
    "name": "accounts/101966824514574841442/locations/17375006377495534857/reviews/Ci9DQUlRQUNvZENodHljRjlvT25Sd1pEVnpiRWxCZHpCMWFrNURUa1pFYUZoRlVsRRAB"
  }, {
    "reviewer": {
      "displayName": "Naif Alruqi"
    },
    "starRating": "FIVE",
    "createTime": "2025-08-24T11:54:33.698632Z",
    "updateTime": "2025-08-24T11:54:33.698632Z",
    "reviewReply": {
      "comment": "๐บ๐๐ป",
      "updateTime": "2025-09-07T22:33:36.996955Z"
    },
    "name": "accounts/101966824514574841442/locations/17375006377495534857/reviews/Ci9DQUlRQUNvZENodHljRjlvT2s1QlVqWXRaRmhSYVRKamVEQkRNVVJMVUdsNGJYYxAB"
  }, {
    "reviewer": {
      "displayName": "ุจุฏุฑ ุงูุนุชูุจู"
    },
    "starRating": "FIVE",
    "comment": "ุตุงููู ููุชุงุฒ ูุงูุทุงูู ููุชุงุฒูู ูู ุงูุงุณุชุงุฐ ุนุจุฏุงููุฑูู ูุจูุจ ู ุฎุงูุฏ ุดุงูุฑ ููู ูููุฏุฑ.\n\n(Translated by Google)\nExcellent salon and excellent staff from Mr. Abdul Karim, Bob and Khaled. Thank you and appreciate you.",
    "createTime": "2025-08-21T10:56:01.091446Z",
    "updateTime": "2025-08-21T10:56:01.091446Z",
    "reviewReply": {
      "comment": "ุดูุฑูุง ูุง ุจุฏุฑ ุนูู ุฑุฃูู ุงูุฌููู ๐น\nูุณุนุฏูุง ุฅูู ูููุช ุงูุชุฌุฑุจุฉ ุนูุฏูุง ุจุงููุณุชูู ุงููู ุชุชููุงู ๐\nูููุงุชู ุชูุฏูุฑ ูุจูุฑ ููุง ูุชุนุทููุง ุญุงูุฒ ููุงุตู ุจููุณ ุงูุฌูุฏุฉ ๐โจ\nุชุดุฑููุง ุจุฒูุงุฑุชู ููุฑุญุจ ููู ุฏุงุฆููุง.",
      "updateTime": "2025-09-07T22:34:02.564298Z"
    },
    "name": "accounts/101966824514574841442/locations/17375006377495534857/reviews/Ci9DQUlRQUNvZENodHljRjlvT21rMGNHeEZXSGMyVVhwVWJ6Tk5ja3hETVRCMldtYxAB"
  }, {
    "reviewer": {
      "displayName": "ุนุจุฏุงูุนุฒูุฒ"
    },
    "starRating": "FIVE",
    "createTime": "2025-08-20T11:52:13.352275Z",
    "updateTime": "2025-08-20T11:52:13.352275Z",
    "reviewReply": {
      "comment": "๐๐ป๐บ",
      "updateTime": "2025-09-07T22:34:08.033900Z"
    },
    "name": "accounts/101966824514574841442/locations/17375006377495534857/reviews/Ci9DQUlRQUNvZENodHljRjlvT2pKQ1VYazRObW8zZDNGMmNFdzNNVXQ1V1VWZmJsRRAB"
  }, {
    "reviewer": {
      "displayName": "ูุญูุฏ ุขู ุญุงุณู"
    },
    "starRating": "FIVE",
    "createTime": "2025-08-19T21:19:03.044391Z",
    "updateTime": "2025-08-19T21:19:03.044391Z",
    "reviewReply": {
      "comment": "โค๏ธ๐๐ป",
      "updateTime": "2025-09-07T22:25:27.233643Z"
    },
    "name": "accounts/101966824514574841442/locations/17375006377495534857/reviews/Ci9DQUlRQUNvZENodHljRjlvT2twRmNsSXhNREJrTVVWclgyZFVVVk5YVVcxSFFXYxAB"
  }, {
    "reviewer": {
      "displayName": "Dr Mohammed A.S"
    },
    "starRating": "THREE",
    "comment": "ุงูู ุฒูุงุฑุฉ ููุตุงููู ุจุบุฑุถ ูุต ุดุนุฑ ูุญูุงู ุฒูุช ููุดุนุฑ. ุนุฌุจูู ุชุตููู ุงููุญูุูุงุณุน ูุญุฏูุซ ู ุดุฑุญ ูุงููุฑุงุณู ูุฑูุญุฉ.\nูู ุชุนุฌุจูู ุงูุงุบุงูู ุงูุนุงููุฉ ูุงููุฒุนุฌุฉุ ุงููุดุท ู ุงูููุต ูุง ูุชู ุงุณุชุจุฏุงููู ุจุนุฏ ูู ุนููู ููุง ุญุชู ุนูู ุงูุฃูู ูุชู ุชุนููููู. ุงูุฃุฎ ุงูุญูุงู ูุงู ูุญุชุฑู ููู ูู ูุญุชุฑู ุงูููุช ุงููุฎุตุต ููุ ุฎูุงู ุญูุงู ุฒูุช ุงูุดุนุฑ ุจูุฎุฏู ุนููู ุงุฎุฑ ูุงุถุทุฑูุช ุงูุชุธุฑ ูขู ุฏูููุฉ ุนุดุงู ุบุณูู ุงูุดุนุฑุ ูุฐุง ุบูุฑ ุงู ุฌูุฏุฉ ูุต ุงูุดุนุฑ ูู ุชูู ุนูู ุงููุณุชูู ุงููุทููุจ.\nุฃุชููู ููุตุงููู ุงูุชูููู ูุงูุชุญุณู ูู ุงููุณุชูุจู.\n\n(Translated by Google)\nMy first visit to the salon for a haircut and oil bath. I liked the design of the shop; it\u0027s spacious, modern, and inviting, and the chairs are comfortable.\nI didn\u0027t like the loud, annoying music. The combs and scissors aren\u0027t replaced after each customer, nor are they even sterilized. The barber was respectful, but he didn\u0027t respect my allotted time. During the oil bath, he was serving another customer, and I had to wait 20 minutes for a hair wash. Furthermore, the quality of the haircut wasn\u0027t up to scratch.\nI wish the salon continued success and continued improvement in the future.",
    "createTime": "2025-08-19T19:47:21.996273Z",
    "updateTime": "2025-08-19T19:47:21.996273Z",
    "reviewReply": {
      "comment": "ุฏูุชูุฑ ูุญูุฏุ ูุดูุฑู ุนูู ุฒูุงุฑุชู ูุชูุตูู ุชุฌุฑุจุชู โ ูููุฏูุฑ ููุชู ูู ูุดุงุฑูุฉ ููุงุญุธุงุชู.\n\nููู ููุฏ ุงูุชูุถูุญ ุฃูู ูุชุจุช ุชููููู ุนูู ูุฑุนูุง ูู ุงูุทุงุฆู ุจูููุง ุงูุฎุฏูุฉ ููุฏูุช ูู ูู ููุฉ. ููุฐุง ูุฏ ูุนุทู ุตูุฑุฉ ุบูุฑ ุฏูููุฉ ุนู ุงููุฑุน.\n\n๐ถ ุงูููุณููู ุฌุฒุก ุฃุณุงุณู ูู ุฃุฌูุงุก ุงูุตุงูููุ ููุฑุงุนู ูููุง ุงูุฐูู ุงูุนุงู. ููุน ุฐููุ ุณูุฑุงุฌุน ูุณุชูู ุงูุตูุช ููุชุฃูุฏ ุฅุฐุง ูุงู ุถูู ุงูููุจูู ุฃู ุจุญุงุฌุฉ ูุถุจุท.\n\n๐งด ุจุงููุณุจุฉ ูุญูุงู ุงูุฒูุชุ ูุญุณุจ ุชูุตูุงุช ุดุฑูุงุช ุงูุนูุงูุฉ ุจุงูุดุนุฑุ ูููุถู ุชุฑู ุงูุฒูุช ุนูู ุงูุดุนุฑ ูู ูขู ุฅูู ูฃู ุฏูููุฉ ูุจู ุงูุบุณููุ ููุฐุง ุฌุฒุก ูู ุฌูุฏุฉ ุงูุฎุฏูุฉ ูููุณ ุฅููุงููุง.\n\nโ๏ธ ุฃุฏูุงุช ุงูุญูุงูุฉ ูุฏููุง ูุชู ุชุนููููุง ุจุดูู ูุณุชูุฑุ ูุฃู ุฎูู ูู ุงูุฅุฌุฑุงุก ูุชู ูุชุงุจุนุชู ููุฑูุง. (ุงูููุฑูุถ ูุน ูู ุนููู ุฃุฏูุงุช ุฌุฏูุฏุฉ ูุนููุฉ ุณูุฑุงุฌุน ูุฐุง ููุนุชุฐุฑ ุนู ุงู ุชูุตูุฑ)\n\n\nูุฃุณู ุฅู ุดุนุฑุช ุฃู ุชุฌุฑุจุชู ูู ุชูู ุจุงููุณุชูู ุงููุทููุจุ ููู ูุคูุฏ ุฃู ูู ููุงุญุธุงุชู ูุญู ุงูุชูุงููุงุ ููุฏููุง ุชูุฏูู ุฎุฏูุฉ ุงุญุชุฑุงููุฉ ุชููู ุจุซูุชู.",
      "updateTime": "2025-08-19T20:22:28.826985Z"
    },
    "name": "accounts/101966824514574841442/locations/17375006377495534857/reviews/Ci9DQUlRQUNvZENodHljRjlvT2xKZmJEWnZTV3hCVGkxcmEyNUdla1J3U1RBMVRrRRAB"
  }, {
    "reviewer": {
      "displayName": "Shfjejjje Sjjsshhsh"
    },
    "starRating": "FIVE",
    "createTime": "2025-08-19T09:28:29.720610Z",
    "updateTime": "2025-08-19T09:28:29.720610Z",
    "reviewReply": {
      "comment": "โค๏ธ๐บ",
      "updateTime": "2025-08-19T20:22:40.257455Z"
    },
    "name": "accounts/101966824514574841442/locations/17375006377495534857/reviews/Ci9DQUlRQUNvZENodHljRjlvT2toYVpWUTFVSGt3V0RkYWVHSlFVbTQyU0ZWaFUyYxAB"
  }, {
    "reviewer": {
      "displayName": "ุงุจูุนุจุฏุงููู ุงูุณุจูุนู"
    },
    "starRating": "ONE",
    "createTime": "2025-08-18T15:26:29.268749Z",
    "updateTime": "2025-08-18T15:26:29.268749Z",
    "reviewReply": {
      "comment": "ุฃุจู ุนุจุฏุงูููุ ูุงุญุธูุง ุฅูู ููุญุชูุง โญ ูุงุญุฏุฉ ุจุฏูู ุฃู ุชุนููู ุฃู ุชูุถูุญ.\nูุญู ูุฑุญุจ ุจุฃู ููุฏ ุฃู ููุงุญุธุงุช ุชุณุงุนุฏูุง ูุชุญุณูุ ููู ุชูููู ุจูุง ุชูุงุตูู ูุง ูุนุทู ุตูุฑุฉ ุนุงุฏูุฉ ุนู ุชุฌุฑุจุชู ููุง ูุณุงุนุฏูุง ูููู ุงููุดููุฉ.\nูุชููู ููู ุชุฒููุฏูุง ุจุณุจุจ ุชูููููุ ูุฃู ูุฏููุง ุฏุงูููุง ุฑุถุง ุนููุงุฆูุง ูุชูุฏูู ุงูุฃูุถู ๐โจ",
      "updateTime": "2025-08-19T20:23:37.693665Z"
    },
    "name": "accounts/101966824514574841442/locations/17375006377495534857/reviews/Ci9DQUlRQUNvZENodHljRjlvT21aS1RUSk5PWFIzYkY5d1JUTk1WM2N5ZURkMFdIYxAB"
  }, {
    "reviewer": {
      "displayName": "hani almaliki"
    },
    "starRating": "FIVE",
    "createTime": "2025-08-16T18:15:35.783029Z",
    "updateTime": "2025-08-16T18:15:35.783029Z",
    "reviewReply": {
      "comment": "โค๏ธ๐๐ป",
      "updateTime": "2025-08-16T22:22:06.374174Z"
    },
    "name": "accounts/101966824514574841442/locations/17375006377495534857/reviews/Ci9DQUlRQUNvZENodHljRjlvT21obU1WTjZNVFV6U2xGT1QycHZiR3BMYTBsR1ptYxAB"
  }, {
    "reviewer": {
      "displayName": "Hmood Alsheim"
    },
    "starRating": "ONE",
    "createTime": "2025-08-16T01:29:35.916975Z",
    "updateTime": "2025-08-16T01:29:35.916975Z",
    "reviewReply": {
      "comment": "ูุณุนุฏูุง ุชููููู ููุดุงุฑูุฉ ุชุฌุฑุจุชู ุทุจุนุงู ุงุฐุง ุฌุฑุจุช ุงูุฎุฏูู ูุงุณุชูุฏุช ูููุง ุ ููู ุงูุชุฑุงุญุงุช ูููู ุจููุงุณุจุฉ ูุฑูุฑู ูู ุฌูุจ ุงููุญู ูุฑูุน ุชูููู ุญุณุงุจู ุงูุช ูุณูุคู ุงูุงู ุงููู ุนู ูุฐุง ุงูุชูููู ูุฑูุน ุญุณุงุจู ูููู ุจุงูุงูุชูุงุฏ ุงููุงุถุญ ุ ุงูุซุฑ ูู 4000 ุชูููู ูููุง ูุฌูู ๐ ูุจุฏู ุงูู ุบูุฑ ูุจุงูู ููุณุช ุงุญุชุฑุงูู ูู ุงุณุชุฎุฏุงู ูุฐุฉ ุงูุฎุงุตูุฉ ",
      "updateTime": "2025-08-16T01:59:07.846044Z"
    },
    "name": "accounts/101966824514574841442/locations/17375006377495534857/reviews/Ci9DQUlRQUNvZENodHljRjlvT2pKMU4yVm9VMjV5YlVrMGRHTXlSWFZNTVdoVVMzYxAB"
  }, {
    "reviewer": {
      "displayName": "Mil."
    },
    "starRating": "FIVE",
    "createTime": "2025-08-15T20:41:14.082725Z",
    "updateTime": "2025-08-15T20:41:14.082725Z",
    "reviewReply": {
      "comment": "๐บโค๏ธ",
      "updateTime": "2025-08-16T22:22:11.856184Z"
    },
    "name": "accounts/101966824514574841442/locations/17375006377495534857/reviews/Ci9DQUlRQUNvZENodHljRjlvT21aS2NFNXBSbnA0YVRsUExWaFpMWFZUVHpoWldFRRAB"
  }, {
    "reviewer": {
      "displayName": "ุนุจุฏุงูุนุฒูุฒ"
    },
    "starRating": "FIVE",
    "comment": "ุตุงููู ูุญุชุฑู ุฌุฏุงู ูุญูุงููู ูุญุชุฑููู ุฌุฏุงู ูููู ุดุงุจ ุฌุงุก ุฌุฏูุฏ ููุตุงููู ูููุงุงุงุงุงุงุงุงุงุงุงุงู ูุงู ุงูู ูุฑุณู ุนุงููุณุงุฑ ุ ุชุฌุฑุจุฉ ุฑุงุญ ุชูุนุงุฏ โค๏ธ๐๐ป\n\n(Translated by Google)\nA very respectable salon and very respectable barbers. There is a young man who came new to the salon and he was a genius. He was the first chair on the left. An experience that will be repeated โค๏ธ๐๐ป",
    "createTime": "2025-08-15T16:51:49.281279Z",
    "updateTime": "2025-08-15T16:51:49.281279Z",
    "reviewReply": {
      "comment": "ุนุจุฏุงูุนุฒูุฒุ ุดูุงุฏุชู ูุณุงู ุนูู ุตุฏุฑูุง! ๐๐ปโค๏ธ\nูููุงููุง ุงูุฌุฏูุฏ (ุนุจุฏุงููู) ูุจุณูุท ุฌุฏูุง ุจููุงูู.\n\nุงููุฑุณู ุงูุฃูู ุนูู ุงููุณุงุฑ ุตุงุฑ ูู ููุจุฉ ุจุนุฏ ุชููููู ๐๐\nููุชุธุฑู ุฏุงุฆููุงุ ูุงูููุงู ููุงูู ุจุฃู ููุช!",
      "updateTime": "2025-08-16T22:23:12.044684Z"
    },
    "name": "accounts/101966824514574841442/locations/17375006377495534857/reviews/Ci9DQUlRQUNvZENodHljRjlvT2xFMFZWUk9UaTB5U2kwMVdtaG9WVlZVVm10UlUwRRAB"
  }, {
    "reviewer": {
      "displayName": "MOD SA"
    },
    "starRating": "FIVE",
    "comment": "ูุง ุดุงุก ุงููู ุชุจุงุฑู ุงููู ุตุงููู ุฌููู ูุดุบููู ุฌููู\nุนุจุฏุงููุฑูู ุญูุงูุชู ุฌุฏุง ุฌูููู\n\n(Translated by Google)\nMasha Allah, Tabarak Allah, a beautiful salon and their work is beautiful. Abdul Karim\u0027s haircut is very beautiful.",
    "createTime": "2025-08-11T13:20:59.120961Z",
    "updateTime": "2025-08-11T13:20:59.120961Z",
    "reviewReply": {
      "comment": "ูุง ุดุงุก ุงููู ุนููู MOD SAุ ููุงูู ูุดุฑุญ ุงูุตุฏุฑ! ๐\nูุตุฑุงุญุฉ ุนุจุฏุงููุฑูู ุฏุงูููุง ูุฏููุง โ๏ธ๐\nุณุนุฏุงุก ุฅู ุชุฌุฑุจุชู ูุงูุช ุจูุฐุง ุงููุณุชููุ ููุดููู ูุฑูุจ ุฅู ุดุงุก ุงููู ๐๐ฅ",
      "updateTime": "2025-08-16T22:23:37.297463Z"
    },
    "name": "accounts/101966824514574841442/locations/17375006377495534857/reviews/Ci9DQUlRQUNvZENodHljRjlvT2xkUldWaGxORFY0VldVMFJXbFZURk5LYlZGNVQwRRAB"
  }, {
    "reviewer": {
      "displayName": "Fnb .x9"
    },
    "starRating": "FIVE",
    "createTime": "2025-08-11T05:12:57.654436Z",
    "updateTime": "2025-08-11T05:12:57.654436Z",
    "reviewReply": {
      "comment": "๐บ๐น",
      "updateTime": "2025-08-11T05:45:42.267766Z"
    },
    "name": "accounts/101966824514574841442/locations/17375006377495534857/reviews/Ci9DQUlRQUNvZENodHljRjlvT21wdU1uRTNPV05WT1dWRE5rZzJVWEJvVUhSdGFVRRAB"
  }]
}